dataflat/__init__.py
dataflat/commons.py
dataflat/exceptions.py
dataflat/flattener_handler.py
dataflat/base/__init__.py
dataflat/base/flattener.py
dataflat/dictionary/__init__.py
dataflat/dictionary/flattener.py
dataflat/pyspark_df/__init__.py
dataflat/pyspark_df/flattener.py
dataflat/utils/__init__.py
dataflat/utils/case_translator.py
dataflat/utils/string.py
dataflat-2.0.0.dist-info/LICENSE
dataflat-2.0.0.dist-info/METADATA
dataflat-2.0.0.dist-info/WHEEL
dataflat-2.0.0.dist-info/top_level.txt
dataflat-2.0.0.dist-info/RECORD
