Metadata-Version: 2.1
Name: dataflat
Version: 2.0.0
Summary: A library to flatten nested data.
Author-email: Juan Rojas <jarojasa97@gmail.com>
License: Apache License
Project-URL: Repository, https://github.com/JuanARojasA/dataflat.git
Project-URL: Issues, https://github.com/JuanARojasA/dataflat/issues
Project-URL: Changelog, https://github.com/JuanARojasA/dataflat/blob/master/CHANGELOG.md
Keywords: flattening,nested,data,pyspark
Classifier: Development Status :: 5 - Production/Stable
Classifier: Intended Audience :: Developers
Classifier: Intended Audience :: Information Technology
Classifier: Intended Audience :: Science/Research
Classifier: License :: OSI Approved :: Apache Software License
Classifier: Natural Language :: English
Classifier: Operating System :: OS Independent
Classifier: Programming Language :: Python :: 3
Classifier: Programming Language :: Python :: 3.10
Classifier: Programming Language :: Python :: 3.11
Classifier: Programming Language :: Python :: 3.12
Classifier: Topic :: Scientific/Engineering
Classifier: Topic :: Software Development :: Libraries
Classifier: Topic :: Software Development :: Libraries :: Python Modules
Classifier: Topic :: Software Development :: Pre-processors
Classifier: Topic :: Utilities
Requires-Python: >=3.10
License-File: LICENSE
Requires-Dist: typeguard ==4.3.0
Provides-Extra: test
Requires-Dist: coverage ==7.6.1 ; extra == 'test'
Requires-Dist: pytest ==8.3.2 ; extra == 'test'
Requires-Dist: numpy ==1.26.4 ; extra == 'test'
Requires-Dist: pandas ==2.0.3 ; extra == 'test'
Requires-Dist: pyspark ==3.5.0 ; extra == 'test'
Requires-Dist: testcontainers ==4.8.0 ; extra == 'test'
